ted2zim/__about__.py
ted2zim/__init__.py
ted2zim/constants.py
ted2zim/entrypoint.py
ted2zim/languages.py
ted2zim/processing.py
ted2zim/scraper.py
ted2zim/utils.py
ted2zim/locale/hi/LC_MESSAGES/messages.po
ted2zim/multi/__init__.py
ted2zim/multi/entrypoint.py
ted2zim/multi/scraper.py
ted2zim/templates/article.html
ted2zim/templates/favicon.png
ted2zim/templates/home.html
ted2zim/templates/assets/app.js
ted2zim/templates/assets/article.css
ted2zim/templates/assets/article.js
ted2zim/templates/assets/db.js
ted2zim/templates/assets/home.css
ted2zim/templates/assets/jquery.min.js
ted2zim/templates/assets/polyfills.js
ted2zim/templates/assets/videojs-ogvjs.js
ted2zim/templates/assets/webp-hero.bundle.js
ted2zim/templates/assets/webp-trigger.js
ted2zim/templates/assets/chosen/chosen-sprite.png
ted2zim/templates/assets/chosen/chosen-sprite@2x.png
ted2zim/templates/assets/chosen/chosen.css
ted2zim/templates/assets/chosen/chosen.jquery.js
ted2zim/templates/assets/chosen/chosen.jquery.min.js
ted2zim/templates/assets/chosen/chosen.min.css
ted2zim/templates/assets/chosen/composer.json
ted2zim/templates/assets/font/Roboto-Black.ttf
ted2zim/templates/assets/font/Roboto-Bold.ttf
ted2zim/templates/assets/font/Roboto-Light.ttf
ted2zim/templates/assets/font/Roboto-LightItalic.ttf
ted2zim/templates/assets/font/Roboto-Regular.ttf
ted2zim/templates/assets/img/TED.png
ted2zim/templates/assets/img/TED_small.png
ted2zim/templates/assets/ogvjs/ogv-decoder-audio-opus-wasm.js
ted2zim/templates/assets/ogvjs/ogv-decoder-audio-opus-wasm.wasm
ted2zim/templates/assets/ogvjs/ogv-decoder-audio-vorbis-wasm.js
ted2zim/templates/assets/ogvjs/ogv-decoder-audio-vorbis-wasm.wasm
ted2zim/templates/assets/ogvjs/ogv-decoder-video-av1-mt-wasm.js
ted2zim/templates/assets/ogvjs/ogv-decoder-video-av1-mt-wasm.wasm
ted2zim/templates/assets/ogvjs/ogv-decoder-video-av1-mt-wasm.worker.js
ted2zim/templates/assets/ogvjs/ogv-decoder-video-av1-wasm.js
ted2zim/templates/assets/ogvjs/ogv-decoder-video-av1-wasm.wasm
ted2zim-3.0.3.dist-info/METADATA
ted2zim-3.0.3.dist-info/WHEEL
ted2zim-3.0.3.dist-info/entry_points.txt
ted2zim-3.0.3.dist-info/licenses/LICENSE
ted2zim-3.0.3.dist-info/RECORD
