Metadata-Version: 2.1
Name: ted2zim
Version: 3.0.3
Summary: Make ZIM file from TED Talks
Project-URL: Donate, https://www.kiwix.org/en/support-us/
Project-URL: Homepage, https://github.com/openzim/ted
Author-email: openZIM <dev@openzim.org>
License: GPL-3.0-or-later
License-File: LICENSE
Keywords: offline,openzim,ted,zim
Classifier: License :: OSI Approved :: GNU General Public License v3 or later (GPLv3+)
Classifier: Programming Language :: Python :: 3
Classifier: Programming Language :: Python :: 3.12
Requires-Python: <3.13,>=3.12
Requires-Dist: beautifulsoup4==4.12.3
Requires-Dist: jinja2==3.1.4
Requires-Dist: kiwixstorage==0.9.0
Requires-Dist: pif==0.8.2
Requires-Dist: python-dateutil==2.9.0.post0
Requires-Dist: python-slugify==8.0.4
Requires-Dist: requests==2.32.3
Requires-Dist: yt-dlp
Requires-Dist: zimscraperlib==3.4.0
Provides-Extra: check
Requires-Dist: pyright==1.1.368; extra == 'check'
Provides-Extra: dev
Requires-Dist: debugpy==1.8.1; extra == 'dev'
Requires-Dist: pre-commit==3.7.1; extra == 'dev'
Requires-Dist: ted2zim[check]; extra == 'dev'
Requires-Dist: ted2zim[lint]; extra == 'dev'
Requires-Dist: ted2zim[scripts]; extra == 'dev'
Requires-Dist: ted2zim[test]; extra == 'dev'
Provides-Extra: lint
Requires-Dist: black==24.4.2; extra == 'lint'
Requires-Dist: ruff==0.4.10; extra == 'lint'
Provides-Extra: scripts
Requires-Dist: invoke==2.2.0; extra == 'scripts'
Provides-Extra: test
Requires-Dist: coverage==7.5.3; extra == 'test'
Requires-Dist: pytest==8.2.2; extra == 'test'
